gosdt-1.0.4.dist-info/WHEEL
gosdt-1.0.4.dist-info/METADATA
gosdt-1.0.4.dist-info/RECORD
gosdt-1.0.4.dist-info/licenses/LICENSE
gosdt/__init__.py
gosdt/_version.pyi
gosdt/_tree.py
gosdt/_binarizer.py
gosdt/_libgosdt.cpython-39-x86_64-linux-gnu.so
gosdt/py.typed
gosdt/_threshold_guessing.py
gosdt/_version.py
gosdt/_classifier.py
gosdt.libs/libtbb-e28f59ed.so.12.15
gosdt.libs/libtbbmalloc-7c327b00.so.2.15
gosdt.libs/libgmp-af761e89.so.10.5.0
