Metadata-Version: 2.1
Name: gosdt
Version: 1.0.4
Summary: Implementation of General Optimal Sparse Decision Tree
Author-Email: Ilias Karimalis <iliaskar@students.cs.ubc.ca>
License: BSD 3-Clause License
Classifier: Intended Audience :: Science/Research
Classifier: Intended Audience :: Developers
Classifier: License :: OSI Approved :: BSD License
Classifier: Operating System :: OS Independent
Classifier: Programming Language :: Python
Classifier: Programming Language :: Python :: 3
Classifier: Programming Language :: Python :: 3 :: Only
Classifier: Programming Language :: Python :: 3.9
Classifier: Programming Language :: Python :: 3.10
Classifier: Programming Language :: Python :: 3.11
Classifier: Programming Language :: Python :: 3.12
Classifier: Topic :: Scientific/Engineering
Classifier: Typing :: Typed
Project-URL: Homepage, https://github.com/ubc-systopia/gosdt-guesses
Project-URL: Bug tracker, https://github.com/ubc-systopia/gosdt-guesses/issues
Project-URL: Discussions, https://github.com/ubc-systopia/gosdt-guesses/discussions
Project-URL: Changelog, https://github.com/ubc-systopia/gosdt-guesses/releases
Requires-Python: >=3.9
Requires-Dist: numpy>=1.24.3
Requires-Dist: scikit-learn>=1.2.2
Requires-Dist: pandas>=2.0.1
Requires-Dist: pytest>=6; extra == "test"
Requires-Dist: pytest-cov>=3; extra == "test"
Requires-Dist: pytest>=6; extra == "dev"
Requires-Dist: pytest-cov>=3; extra == "dev"
Provides-Extra: test
Provides-Extra: dev
